{"articleId_0":{"data":{"title":"Article 0","category":"Sample Category","author":"Author Name","text":"Lorem ipsum dolor sit amet, consectetur adipiscing elit. Nulla ultrices dolor justo, vel egestas nunc mattis vitae. Aliquam erat volutpat. Nam faucibus urna non arcu ultrices efficitur. Phasellus ut aliquet odio, suscipit pulvinar purus. Proin a consequat augue. Praesent finibus odio vel pretium consequat. Lorem ipsum dolor sit amet, consectetur adipiscing elit. Nulla ultrices dolor justo, vel egestas nunc mattis vitae. Aliquam erat volutpat. Nam faucibus urna non arcu ultrices efficitur. Phasellus ut aliquet odio, suscipit pulvinar purus. Proin a consequat augue. Praesent finibus odio vel pretium consequat. Lorem ipsum dolor sit amet, consectetur adipiscing elit. Nulla ultrices dolor justo, vel egestas nunc mattis vitae. Aliquam erat volutpat. Nam faucibus urna non arcu ultrices efficitur. Phasellus ut aliquet odio, suscipit pulvinar purus. Proin a consequat augue. Praesent finibus odio vel pretium consequat. Lorem ipsum dolor sit amet, consectetur adipiscing elit. Nulla ultrices dolor justo, vel egestas nunc mattis vitae. Aliquam erat volutpat. Nam faucibus urna non arcu ultrices efficitur. Phasellus ut aliquet odio, suscipit pulvinar purus. Proin a consequat augue. Praesent finibus odio vel pretium consequat. Lorem ipsum dolor sit amet, consectetur adipiscing elit. Nulla ultrices dolor justo, vel egestas nunc mattis vitae. Aliquam erat volutpat. Nam faucibus urna non arcu ultrices efficitur. Phasellus ut aliquet odio, suscipit pulvinar purus. Proin a consequat augue. Praesent finibus odio vel pretium consequat. Lorem ipsum dolor sit amet, consectetur adipiscing elit. Nulla ultrices dolor justo, vel egestas nunc mattis vitae. Aliquam erat volutpat. Nam faucibus urna non arcu ultrices efficitur. Phasellus ut aliquet odio, suscipit pulvinar purus. Proin a consequat augue. Praesent finibus odio vel pretium consequat. Lorem ipsum dolor sit amet, consectetur adipiscing elit. Nulla ultrices dolor justo, vel egestas nunc mattis vitae. Aliquam erat volutpat. Nam faucibus urna non arcu ultrices efficitur. Phasellus ut aliquet odio, suscipit pulvinar purus. Proin a consequat augue. Praesent finibus odio vel pretium consequat. Lorem ipsum dolor sit amet, consectetur adipiscing elit. Nulla ultrices dolor justo, vel egestas nunc mattis vitae. Aliquam erat volutpat. Nam faucibus urna non arcu ultrices efficitur. Phasellus ut aliquet odio, suscipit pulvinar purus. Proin a consequat augue. Praesent finibus odio vel pretium consequat. Lorem ipsum dolor sit amet, consecte","image":"./images/articles/0.jpg","date_added":"2022-06-28"},"metadata":{"id":"articleId_0","type":"article","tags":["tag_0","tag_1","tag_2","tag_3"],"is_active":true}},"articleId_1":{"data":{"title":"Article 1","category":"Sample Category","author":"Author Name","text":"Lorem ipsum dolor sit amet, consectetur adipiscing elit. Nulla ultrices dolor justo, vel egestas nunc mattis vitae. Aliquam erat volutpat. Nam faucibus urna non arcu ultrices efficitur. Phasellus ut aliquet odio, suscipit pulvinar purus. Proin a consequat augue. Praesent finibus odio vel pretium consequat. Lorem ipsum dolor sit amet, consectetur adipiscing elit. Nulla ultrices dolor justo, vel egestas nunc mattis vitae. Aliquam erat volutpat. Nam faucibus urna non arcu ultrices efficitur. Phasellus ut aliquet odio, suscipit pulvinar purus. Proin a consequat augue. Praesent finibus odio vel pretium consequat. Lorem ipsum dolor sit amet, consectetur adipiscing elit. Nulla ultrices dolor justo, vel egestas nunc mattis vitae. Aliquam erat volutpat. Nam faucibus urna non arcu ultrices efficitur. Phasellus ut aliquet odio, suscipit pulvinar purus. Proin a consequat augue. Praesent finibus odio vel pretium consequat. Lorem ipsum dolor sit amet, consectetur adipiscing elit. Nulla ultrices dolor justo, vel egestas nunc mattis vitae. Aliquam erat volutpat. Nam faucibus urna non arcu ultrices efficitur. Phasellus ut aliquet odio, suscipit pulvinar purus. Proin a consequat augue. Praesent finibus odio vel pretium consequat. Lorem ipsum dolor sit amet, consectetur adipiscing elit. Nulla ultrices dolor justo, vel egestas nunc mattis vitae. Aliquam erat volutpat. Nam faucibus urna non arcu ultrices efficitur. Phasellus ut aliquet odio, suscipit pulvinar purus. Proin a consequat augue. Praesent finibus odio vel pretium consequat. Lorem ipsum dolor sit amet, consectetur adipiscing elit. Nulla ultrices dolor justo, vel egestas nunc mattis vitae. Aliquam erat volutpat. Nam faucibus urna non arcu ultrices efficitur. Phasellus ut aliquet odio, suscipit pulvinar purus. Proin a consequat augue. Praesent finibus odio vel pretium consequat. Lorem ipsum dolor sit amet, consectetur adipiscing elit. Nulla ultrices dolor justo, vel egestas nunc mattis vitae. Aliquam erat volutpat. Nam faucibus urna non arcu ultrices efficitur. Phasellus ut aliquet odio, suscipit pulvinar purus. Proin a consequat augue. Praesent finibus odio vel pretium consequat. Lorem ipsum dolor sit amet, consectetur adipiscing elit. Nulla ultrices dolor justo, vel egestas nunc mattis vitae. Aliquam erat volutpat. Nam faucibus urna non arcu ultrices efficitur. Phasellus ut aliquet odio, suscipit pulvinar purus. Proin a consequat augue. Praesent finibus odio vel pretium consequat. Lorem ipsum dolor sit amet, consecte","image":"./images/articles/1.jpg","date_added":"2022-06-28"},"metadata":{"id":"articleId_1","type":"article","tags":["tag_0","tag_1","tag_2","tag_3"],"is_active":true}},"articleId_2":{"data":{"title":"Article 2","category":"Sample Category","author":"Author Name","text":"Lorem ipsum dolor sit amet, consectetur adipiscing elit. Nulla ultrices dolor justo, vel egestas nunc mattis vitae. Aliquam erat volutpat. Nam faucibus urna non arcu ultrices efficitur. Phasellus ut aliquet odio, suscipit pulvinar purus. Proin a consequat augue. Praesent finibus odio vel pretium consequat. Lorem ipsum dolor sit amet, consectetur adipiscing elit. Nulla ultrices dolor justo, vel egestas nunc mattis vitae. Aliquam erat volutpat. Nam faucibus urna non arcu ultrices efficitur. Phasellus ut aliquet odio, suscipit pulvinar purus. Proin a consequat augue. Praesent finibus odio vel pretium consequat. Lorem ipsum dolor sit amet, consectetur adipiscing elit. Nulla ultrices dolor justo, vel egestas nunc mattis vitae. Aliquam erat volutpat. Nam faucibus urna non arcu ultrices efficitur. Phasellus ut aliquet odio, suscipit pulvinar purus. Proin a consequat augue. Praesent finibus odio vel pretium consequat. Lorem ipsum dolor sit amet, consectetur adipiscing elit. Nulla ultrices dolor justo, vel egestas nunc mattis vitae. Aliquam erat volutpat. Nam faucibus urna non arcu ultrices efficitur. Phasellus ut aliquet odio, suscipit pulvinar purus. Proin a consequat augue. Praesent finibus odio vel pretium consequat. Lorem ipsum dolor sit amet, consectetur adipiscing elit. Nulla ultrices dolor justo, vel egestas nunc mattis vitae. Aliquam erat volutpat. Nam faucibus urna non arcu ultrices efficitur. Phasellus ut aliquet odio, suscipit pulvinar purus. Proin a consequat augue. Praesent finibus odio vel pretium consequat. Lorem ipsum dolor sit amet, consectetur adipiscing elit. Nulla ultrices dolor justo, vel egestas nunc mattis vitae. Aliquam erat volutpat. Nam faucibus urna non arcu ultrices efficitur. Phasellus ut aliquet odio, suscipit pulvinar purus. Proin a consequat augue. Praesent finibus odio vel pretium consequat. Lorem ipsum dolor sit amet, consectetur adipiscing elit. Nulla ultrices dolor justo, vel egestas nunc mattis vitae. Aliquam erat volutpat. Nam faucibus urna non arcu ultrices efficitur. Phasellus ut aliquet odio, suscipit pulvinar purus. Proin a consequat augue. Praesent finibus odio vel pretium consequat. Lorem ipsum dolor sit amet, consectetur adipiscing elit. Nulla ultrices dolor justo, vel egestas nunc mattis vitae. Aliquam erat volutpat. Nam faucibus urna non arcu ultrices efficitur. Phasellus ut aliquet odio, suscipit pulvinar purus. Proin a consequat augue. Praesent finibus odio vel pretium consequat. Lorem ipsum dolor sit amet, consecte","image":"./images/articles/2.jpg","date_added":"2022-06-28"},"metadata":{"id":"articleId_2","type":"article","tags":["tag_0","tag_1","tag_2","tag_3"],"is_active":true}},"articleId_3":{"data":{"title":"Article 3","category":"Sample Category","author":"Author Name","text":"Lorem ipsum dolor sit amet, consectetur adipiscing elit. Nulla ultrices dolor justo, vel egestas nunc mattis vitae. Aliquam erat volutpat. Nam faucibus urna non arcu ultrices efficitur. Phasellus ut aliquet odio, suscipit pulvinar purus. Proin a consequat augue. Praesent finibus odio vel pretium consequat. Lorem ipsum dolor sit amet, consectetur adipiscing elit. Nulla ultrices dolor justo, vel egestas nunc mattis vitae. Aliquam erat volutpat. Nam faucibus urna non arcu ultrices efficitur. Phasellus ut aliquet odio, suscipit pulvinar purus. Proin a consequat augue. Praesent finibus odio vel pretium consequat. Lorem ipsum dolor sit amet, consectetur adipiscing elit. Nulla ultrices dolor justo, vel egestas nunc mattis vitae. Aliquam erat volutpat. Nam faucibus urna non arcu ultrices efficitur. Phasellus ut aliquet odio, suscipit pulvinar purus. Proin a consequat augue. Praesent finibus odio vel pretium consequat. Lorem ipsum dolor sit amet, consectetur adipiscing elit. Nulla ultrices dolor justo, vel egestas nunc mattis vitae. Aliquam erat volutpat. Nam faucibus urna non arcu ultrices efficitur. Phasellus ut aliquet odio, suscipit pulvinar purus. Proin a consequat augue. Praesent finibus odio vel pretium consequat. Lorem ipsum dolor sit amet, consectetur adipiscing elit. Nulla ultrices dolor justo, vel egestas nunc mattis vitae. Aliquam erat volutpat. Nam faucibus urna non arcu ultrices efficitur. Phasellus ut aliquet odio, suscipit pulvinar purus. Proin a consequat augue. Praesent finibus odio vel pretium consequat. Lorem ipsum dolor sit amet, consectetur adipiscing elit. Nulla ultrices dolor justo, vel egestas nunc mattis vitae. Aliquam erat volutpat. Nam faucibus urna non arcu ultrices efficitur. Phasellus ut aliquet odio, suscipit pulvinar purus. Proin a consequat augue. Praesent finibus odio vel pretium consequat. Lorem ipsum dolor sit amet, consectetur adipiscing elit. Nulla ultrices dolor justo, vel egestas nunc mattis vitae. Aliquam erat volutpat. Nam faucibus urna non arcu ultrices efficitur. Phasellus ut aliquet odio, suscipit pulvinar purus. Proin a consequat augue. Praesent finibus odio vel pretium consequat. Lorem ipsum dolor sit amet, consectetur adipiscing elit. Nulla ultrices dolor justo, vel egestas nunc mattis vitae. Aliquam erat volutpat. Nam faucibus urna non arcu ultrices efficitur. Phasellus ut aliquet odio, suscipit pulvinar purus. Proin a consequat augue. Praesent finibus odio vel pretium consequat. Lorem ipsum dolor sit amet, consecte","image":"./images/articles/3.jpg","date_added":"2022-06-28"},"metadata":{"id":"articleId_3","type":"article","tags":["tag_0","tag_1","tag_2","tag_3"],"is_active":true}},"articleId_4":{"data":{"title":"Article 4","category":"Sample Category","author":"Author Name","text":"Lorem ipsum dolor sit amet, consectetur adipiscing elit. Nulla ultrices dolor justo, vel egestas nunc mattis vitae. Aliquam erat volutpat. Nam faucibus urna non arcu ultrices efficitur. Phasellus ut aliquet odio, suscipit pulvinar purus. Proin a consequat augue. Praesent finibus odio vel pretium consequat. Lorem ipsum dolor sit amet, consectetur adipiscing elit. Nulla ultrices dolor justo, vel egestas nunc mattis vitae. Aliquam erat volutpat. Nam faucibus urna non arcu ultrices efficitur. Phasellus ut aliquet odio, suscipit pulvinar purus. Proin a consequat augue. Praesent finibus odio vel pretium consequat. Lorem ipsum dolor sit amet, consectetur adipiscing elit. Nulla ultrices dolor justo, vel egestas nunc mattis vitae. Aliquam erat volutpat. Nam faucibus urna non arcu ultrices efficitur. Phasellus ut aliquet odio, suscipit pulvinar purus. Proin a consequat augue. Praesent finibus odio vel pretium consequat. Lorem ipsum dolor sit amet, consectetur adipiscing elit. Nulla ultrices dolor justo, vel egestas nunc mattis vitae. Aliquam erat volutpat. Nam faucibus urna non arcu ultrices efficitur. Phasellus ut aliquet odio, suscipit pulvinar purus. Proin a consequat augue. Praesent finibus odio vel pretium consequat. Lorem ipsum dolor sit amet, consectetur adipiscing elit. Nulla ultrices dolor justo, vel egestas nunc mattis vitae. Aliquam erat volutpat. Nam faucibus urna non arcu ultrices efficitur. Phasellus ut aliquet odio, suscipit pulvinar purus. Proin a consequat augue. Praesent finibus odio vel pretium consequat. Lorem ipsum dolor sit amet, consectetur adipiscing elit. Nulla ultrices dolor justo, vel egestas nunc mattis vitae. Aliquam erat volutpat. Nam faucibus urna non arcu ultrices efficitur. Phasellus ut aliquet odio, suscipit pulvinar purus. Proin a consequat augue. Praesent finibus odio vel pretium consequat. Lorem ipsum dolor sit amet, consectetur adipiscing elit. Nulla ultrices dolor justo, vel egestas nunc mattis vitae. Aliquam erat volutpat. Nam faucibus urna non arcu ultrices efficitur. Phasellus ut aliquet odio, suscipit pulvinar purus. Proin a consequat augue. Praesent finibus odio vel pretium consequat. Lorem ipsum dolor sit amet, consectetur adipiscing elit. Nulla ultrices dolor justo, vel egestas nunc mattis vitae. Aliquam erat volutpat. Nam faucibus urna non arcu ultrices efficitur. Phasellus ut aliquet odio, suscipit pulvinar purus. Proin a consequat augue. Praesent finibus odio vel pretium consequat. Lorem ipsum dolor sit amet, consecte","image":"./images/articles/4.jpg","date_added":"2022-06-28"},"metadata":{"id":"articleId_4","type":"article","tags":["tag_0","tag_1","tag_2","tag_3"],"is_active":true}},"articleId_5":{"data":{"title":"Article 5","category":"Sample Category","author":"Author Name","text":"Lorem ipsum dolor sit amet, consectetur adipiscing elit. Nulla ultrices dolor justo, vel egestas nunc mattis vitae. Aliquam erat volutpat. Nam faucibus urna non arcu ultrices efficitur. Phasellus ut aliquet odio, suscipit pulvinar purus. Proin a consequat augue. Praesent finibus odio vel pretium consequat. Lorem ipsum dolor sit amet, consectetur adipiscing elit. Nulla ultrices dolor justo, vel egestas nunc mattis vitae. Aliquam erat volutpat. Nam faucibus urna non arcu ultrices efficitur. Phasellus ut aliquet odio, suscipit pulvinar purus. Proin a consequat augue. Praesent finibus odio vel pretium consequat. Lorem ipsum dolor sit amet, consectetur adipiscing elit. Nulla ultrices dolor justo, vel egestas nunc mattis vitae. Aliquam erat volutpat. Nam faucibus urna non arcu ultrices efficitur. Phasellus ut aliquet odio, suscipit pulvinar purus. Proin a consequat augue. Praesent finibus odio vel pretium consequat. Lorem ipsum dolor sit amet, consectetur adipiscing elit. Nulla ultrices dolor justo, vel egestas nunc mattis vitae. Aliquam erat volutpat. Nam faucibus urna non arcu ultrices efficitur. Phasellus ut aliquet odio, suscipit pulvinar purus. Proin a consequat augue. Praesent finibus odio vel pretium consequat. Lorem ipsum dolor sit amet, consectetur adipiscing elit. Nulla ultrices dolor justo, vel egestas nunc mattis vitae. Aliquam erat volutpat. Nam faucibus urna non arcu ultrices efficitur. Phasellus ut aliquet odio, suscipit pulvinar purus. Proin a consequat augue. Praesent finibus odio vel pretium consequat. Lorem ipsum dolor sit amet, consectetur adipiscing elit. Nulla ultrices dolor justo, vel egestas nunc mattis vitae. Aliquam erat volutpat. Nam faucibus urna non arcu ultrices efficitur. Phasellus ut aliquet odio, suscipit pulvinar purus. Proin a consequat augue. Praesent finibus odio vel pretium consequat. Lorem ipsum dolor sit amet, consectetur adipiscing elit. Nulla ultrices dolor justo, vel egestas nunc mattis vitae. Aliquam erat volutpat. Nam faucibus urna non arcu ultrices efficitur. Phasellus ut aliquet odio, suscipit pulvinar purus. Proin a consequat augue. Praesent finibus odio vel pretium consequat. Lorem ipsum dolor sit amet, consectetur adipiscing elit. Nulla ultrices dolor justo, vel egestas nunc mattis vitae. Aliquam erat volutpat. Nam faucibus urna non arcu ultrices efficitur. Phasellus ut aliquet odio, suscipit pulvinar purus. Proin a consequat augue. Praesent finibus odio vel pretium consequat. Lorem ipsum dolor sit amet, consecte","image":"./images/articles/5.jpg","date_added":"2022-06-28"},"metadata":{"id":"articleId_5","type":"article","tags":["tag_0","tag_1","tag_2","tag_3"],"is_active":true}},"articleId_6":{"data":{"title":"Article 6","category":"Sample Category","author":"Author Name","text":"Lorem ipsum dolor sit amet, consectetur adipiscing elit. Nulla ultrices dolor justo, vel egestas nunc mattis vitae. Aliquam erat volutpat. Nam faucibus urna non arcu ultrices efficitur. Phasellus ut aliquet odio, suscipit pulvinar purus. Proin a consequat augue. Praesent finibus odio vel pretium consequat. Lorem ipsum dolor sit amet, consectetur adipiscing elit. Nulla ultrices dolor justo, vel egestas nunc mattis vitae. Aliquam erat volutpat. Nam faucibus urna non arcu ultrices efficitur. Phasellus ut aliquet odio, suscipit pulvinar purus. Proin a consequat augue. Praesent finibus odio vel pretium consequat. Lorem ipsum dolor sit amet, consectetur adipiscing elit. Nulla ultrices dolor justo, vel egestas nunc mattis vitae. Aliquam erat volutpat. Nam faucibus urna non arcu ultrices efficitur. Phasellus ut aliquet odio, suscipit pulvinar purus. Proin a consequat augue. Praesent finibus odio vel pretium consequat. Lorem ipsum dolor sit amet, consectetur adipiscing elit. Nulla ultrices dolor justo, vel egestas nunc mattis vitae. Aliquam erat volutpat. Nam faucibus urna non arcu ultrices efficitur. Phasellus ut aliquet odio, suscipit pulvinar purus. Proin a consequat augue. Praesent finibus odio vel pretium consequat. Lorem ipsum dolor sit amet, consectetur adipiscing elit. Nulla ultrices dolor justo, vel egestas nunc mattis vitae. Aliquam erat volutpat. Nam faucibus urna non arcu ultrices efficitur. Phasellus ut aliquet odio, suscipit pulvinar purus. Proin a consequat augue. Praesent finibus odio vel pretium consequat. Lorem ipsum dolor sit amet, consectetur adipiscing elit. Nulla ultrices dolor justo, vel egestas nunc mattis vitae. Aliquam erat volutpat. Nam faucibus urna non arcu ultrices efficitur. Phasellus ut aliquet odio, suscipit pulvinar purus. Proin a consequat augue. Praesent finibus odio vel pretium consequat. Lorem ipsum dolor sit amet, consectetur adipiscing elit. Nulla ultrices dolor justo, vel egestas nunc mattis vitae. Aliquam erat volutpat. Nam faucibus urna non arcu ultrices efficitur. Phasellus ut aliquet odio, suscipit pulvinar purus. Proin a consequat augue. Praesent finibus odio vel pretium consequat. Lorem ipsum dolor sit amet, consectetur adipiscing elit. Nulla ultrices dolor justo, vel egestas nunc mattis vitae. Aliquam erat volutpat. Nam faucibus urna non arcu ultrices efficitur. Phasellus ut aliquet odio, suscipit pulvinar purus. Proin a consequat augue. Praesent finibus odio vel pretium consequat. Lorem ipsum dolor sit amet, consecte","image":"./images/articles/6.jpg","date_added":"2022-06-28"},"metadata":{"id":"articleId_6","type":"article","tags":["tag_0","tag_1","tag_2","tag_3"],"is_active":true}},"articleId_7":{"data":{"title":"Article 7","category":"Sample Category","author":"Author Name","text":"Lorem ipsum dolor sit amet, consectetur adipiscing elit. Nulla ultrices dolor justo, vel egestas nunc mattis vitae. Aliquam erat volutpat. Nam faucibus urna non arcu ultrices efficitur. Phasellus ut aliquet odio, suscipit pulvinar purus. Proin a consequat augue. Praesent finibus odio vel pretium consequat. Lorem ipsum dolor sit amet, consectetur adipiscing elit. Nulla ultrices dolor justo, vel egestas nunc mattis vitae. Aliquam erat volutpat. Nam faucibus urna non arcu ultrices efficitur. Phasellus ut aliquet odio, suscipit pulvinar purus. Proin a consequat augue. Praesent finibus odio vel pretium consequat. Lorem ipsum dolor sit amet, consectetur adipiscing elit. Nulla ultrices dolor justo, vel egestas nunc mattis vitae. Aliquam erat volutpat. Nam faucibus urna non arcu ultrices efficitur. Phasellus ut aliquet odio, suscipit pulvinar purus. Proin a consequat augue. Praesent finibus odio vel pretium consequat. Lorem ipsum dolor sit amet, consectetur adipiscing elit. Nulla ultrices dolor justo, vel egestas nunc mattis vitae. Aliquam erat volutpat. Nam faucibus urna non arcu ultrices efficitur. Phasellus ut aliquet odio, suscipit pulvinar purus. Proin a consequat augue. Praesent finibus odio vel pretium consequat. Lorem ipsum dolor sit amet, consectetur adipiscing elit. Nulla ultrices dolor justo, vel egestas nunc mattis vitae. Aliquam erat volutpat. Nam faucibus urna non arcu ultrices efficitur. Phasellus ut aliquet odio, suscipit pulvinar purus. Proin a consequat augue. Praesent finibus odio vel pretium consequat. Lorem ipsum dolor sit amet, consectetur adipiscing elit. Nulla ultrices dolor justo, vel egestas nunc mattis vitae. Aliquam erat volutpat. Nam faucibus urna non arcu ultrices efficitur. Phasellus ut aliquet odio, suscipit pulvinar purus. Proin a consequat augue. Praesent finibus odio vel pretium consequat. Lorem ipsum dolor sit amet, consectetur adipiscing elit. Nulla ultrices dolor justo, vel egestas nunc mattis vitae. Aliquam erat volutpat. Nam faucibus urna non arcu ultrices efficitur. Phasellus ut aliquet odio, suscipit pulvinar purus. Proin a consequat augue. Praesent finibus odio vel pretium consequat. Lorem ipsum dolor sit amet, consectetur adipiscing elit. Nulla ultrices dolor justo, vel egestas nunc mattis vitae. Aliquam erat volutpat. Nam faucibus urna non arcu ultrices efficitur. Phasellus ut aliquet odio, suscipit pulvinar purus. Proin a consequat augue. Praesent finibus odio vel pretium consequat. Lorem ipsum dolor sit amet, consecte","image":"./images/articles/7.jpg","date_added":"2022-06-28"},"metadata":{"id":"articleId_7","type":"article","tags":["tag_0","tag_1","tag_2","tag_3"],"is_active":true}},"articleId_8":{"data":{"title":"Article 8","category":"Sample Category","author":"Author Name","text":"Lorem ipsum dolor sit amet, consectetur adipiscing elit. Nulla ultrices dolor justo, vel egestas nunc mattis vitae. Aliquam erat volutpat. Nam faucibus urna non arcu ultrices efficitur. Phasellus ut aliquet odio, suscipit pulvinar purus. Proin a consequat augue. Praesent finibus odio vel pretium consequat. Lorem ipsum dolor sit amet, consectetur adipiscing elit. Nulla ultrices dolor justo, vel egestas nunc mattis vitae. Aliquam erat volutpat. Nam faucibus urna non arcu ultrices efficitur. Phasellus ut aliquet odio, suscipit pulvinar purus. Proin a consequat augue. Praesent finibus odio vel pretium consequat. Lorem ipsum dolor sit amet, consectetur adipiscing elit. Nulla ultrices dolor justo, vel egestas nunc mattis vitae. Aliquam erat volutpat. Nam faucibus urna non arcu ultrices efficitur. Phasellus ut aliquet odio, suscipit pulvinar purus. Proin a consequat augue. Praesent finibus odio vel pretium consequat. Lorem ipsum dolor sit amet, consectetur adipiscing elit. Nulla ultrices dolor justo, vel egestas nunc mattis vitae. Aliquam erat volutpat. Nam faucibus urna non arcu ultrices efficitur. Phasellus ut aliquet odio, suscipit pulvinar purus. Proin a consequat augue. Praesent finibus odio vel pretium consequat. Lorem ipsum dolor sit amet, consectetur adipiscing elit. Nulla ultrices dolor justo, vel egestas nunc mattis vitae. Aliquam erat volutpat. Nam faucibus urna non arcu ultrices efficitur. Phasellus ut aliquet odio, suscipit pulvinar purus. Proin a consequat augue. Praesent finibus odio vel pretium consequat. Lorem ipsum dolor sit amet, consectetur adipiscing elit. Nulla ultrices dolor justo, vel egestas nunc mattis vitae. Aliquam erat volutpat. Nam faucibus urna non arcu ultrices efficitur. Phasellus ut aliquet odio, suscipit pulvinar purus. Proin a consequat augue. Praesent finibus odio vel pretium consequat. Lorem ipsum dolor sit amet, consectetur adipiscing elit. Nulla ultrices dolor justo, vel egestas nunc mattis vitae. Aliquam erat volutpat. Nam faucibus urna non arcu ultrices efficitur. Phasellus ut aliquet odio, suscipit pulvinar purus. Proin a consequat augue. Praesent finibus odio vel pretium consequat. Lorem ipsum dolor sit amet, consectetur adipiscing elit. Nulla ultrices dolor justo, vel egestas nunc mattis vitae. Aliquam erat volutpat. Nam faucibus urna non arcu ultrices efficitur. Phasellus ut aliquet odio, suscipit pulvinar purus. Proin a consequat augue. Praesent finibus odio vel pretium consequat. Lorem ipsum dolor sit amet, consecte","image":"./images/articles/8.jpg","date_added":"2022-06-28"},"metadata":{"id":"articleId_8","type":"article","tags":["tag_0","tag_1","tag_2","tag_3"],"is_active":true}},"articleId_9":{"data":{"title":"Article 9","category":"Sample Category","author":"Author Name","text":"Lorem ipsum dolor sit amet, consectetur adipiscing elit. Nulla ultrices dolor justo, vel egestas nunc mattis vitae. Aliquam erat volutpat. Nam faucibus urna non arcu ultrices efficitur. Phasellus ut aliquet odio, suscipit pulvinar purus. Proin a consequat augue. Praesent finibus odio vel pretium consequat. Lorem ipsum dolor sit amet, consectetur adipiscing elit. Nulla ultrices dolor justo, vel egestas nunc mattis vitae. Aliquam erat volutpat. Nam faucibus urna non arcu ultrices efficitur. Phasellus ut aliquet odio, suscipit pulvinar purus. Proin a consequat augue. Praesent finibus odio vel pretium consequat. Lorem ipsum dolor sit amet, consectetur adipiscing elit. Nulla ultrices dolor justo, vel egestas nunc mattis vitae. Aliquam erat volutpat. Nam faucibus urna non arcu ultrices efficitur. Phasellus ut aliquet odio, suscipit pulvinar purus. Proin a consequat augue. Praesent finibus odio vel pretium consequat. Lorem ipsum dolor sit amet, consectetur adipiscing elit. Nulla ultrices dolor justo, vel egestas nunc mattis vitae. Aliquam erat volutpat. Nam faucibus urna non arcu ultrices efficitur. Phasellus ut aliquet odio, suscipit pulvinar purus. Proin a consequat augue. Praesent finibus odio vel pretium consequat. Lorem ipsum dolor sit amet, consectetur adipiscing elit. Nulla ultrices dolor justo, vel egestas nunc mattis vitae. Aliquam erat volutpat. Nam faucibus urna non arcu ultrices efficitur. Phasellus ut aliquet odio, suscipit pulvinar purus. Proin a consequat augue. Praesent finibus odio vel pretium consequat. Lorem ipsum dolor sit amet, consectetur adipiscing elit. Nulla ultrices dolor justo, vel egestas nunc mattis vitae. Aliquam erat volutpat. Nam faucibus urna non arcu ultrices efficitur. Phasellus ut aliquet odio, suscipit pulvinar purus. Proin a consequat augue. Praesent finibus odio vel pretium consequat. Lorem ipsum dolor sit amet, consectetur adipiscing elit. Nulla ultrices dolor justo, vel egestas nunc mattis vitae. Aliquam erat volutpat. Nam faucibus urna non arcu ultrices efficitur. Phasellus ut aliquet odio, suscipit pulvinar purus. Proin a consequat augue. Praesent finibus odio vel pretium consequat. Lorem ipsum dolor sit amet, consectetur adipiscing elit. Nulla ultrices dolor justo, vel egestas nunc mattis vitae. Aliquam erat volutpat. Nam faucibus urna non arcu ultrices efficitur. Phasellus ut aliquet odio, suscipit pulvinar purus. Proin a consequat augue. Praesent finibus odio vel pretium consequat. Lorem ipsum dolor sit amet, consecte","image":"./images/articles/9.jpg","date_added":"2022-06-28"},"metadata":{"id":"articleId_9","type":"article","tags":["tag_0","tag_1","tag_2","tag_3"],"is_active":true}},"articleId_10":{"data":{"title":"Article 10","category":"Sample Category","author":"Author Name","text":"Lorem ipsum dolor sit amet, consectetur adipiscing elit. Nulla ultrices dolor justo, vel egestas nunc mattis vitae. Aliquam erat volutpat. Nam faucibus urna non arcu ultrices efficitur. Phasellus ut aliquet odio, suscipit pulvinar purus. Proin a consequat augue. Praesent finibus odio vel pretium consequat. Lorem ipsum dolor sit amet, consectetur adipiscing elit. Nulla ultrices dolor justo, vel egestas nunc mattis vitae. Aliquam erat volutpat. Nam faucibus urna non arcu ultrices efficitur. Phasellus ut aliquet odio, suscipit pulvinar purus. Proin a consequat augue. Praesent finibus odio vel pretium consequat. Lorem ipsum dolor sit amet, consectetur adipiscing elit. Nulla ultrices dolor justo, vel egestas nunc mattis vitae. Aliquam erat volutpat. Nam faucibus urna non arcu ultrices efficitur. Phasellus ut aliquet odio, suscipit pulvinar purus. Proin a consequat augue. Praesent finibus odio vel pretium consequat. Lorem ipsum dolor sit amet, consectetur adipiscing elit. Nulla ultrices dolor justo, vel egestas nunc mattis vitae. Aliquam erat volutpat. Nam faucibus urna non arcu ultrices efficitur. Phasellus ut aliquet odio, suscipit pulvinar purus. Proin a consequat augue. Praesent finibus odio vel pretium consequat. Lorem ipsum dolor sit amet, consectetur adipiscing elit. Nulla ultrices dolor justo, vel egestas nunc mattis vitae. Aliquam erat volutpat. Nam faucibus urna non arcu ultrices efficitur. Phasellus ut aliquet odio, suscipit pulvinar purus. Proin a consequat augue. Praesent finibus odio vel pretium consequat. Lorem ipsum dolor sit amet, consectetur adipiscing elit. Nulla ultrices dolor justo, vel egestas nunc mattis vitae. Aliquam erat volutpat. Nam faucibus urna non arcu ultrices efficitur. Phasellus ut aliquet odio, suscipit pulvinar purus. Proin a consequat augue. Praesent finibus odio vel pretium consequat. Lorem ipsum dolor sit amet, consectetur adipiscing elit. Nulla ultrices dolor justo, vel egestas nunc mattis vitae. Aliquam erat volutpat. Nam faucibus urna non arcu ultrices efficitur. Phasellus ut aliquet odio, suscipit pulvinar purus. Proin a consequat augue. Praesent finibus odio vel pretium consequat. Lorem ipsum dolor sit amet, consectetur adipiscing elit. Nulla ultrices dolor justo, vel egestas nunc mattis vitae. Aliquam erat volutpat. Nam faucibus urna non arcu ultrices efficitur. Phasellus ut aliquet odio, suscipit pulvinar purus. Proin a consequat augue. Praesent finibus odio vel pretium consequat. Lorem ipsum dolor sit amet, consecte","image":"./images/articles/10.jpg","date_added":"2022-06-28"},"metadata":{"id":"articleId_10","type":"article","tags":["tag_0","tag_1","tag_2","tag_3"],"is_active":true}},"articleId_11":{"data":{"title":"Article 11","category":"Sample Category","author":"Author Name","text":"Lorem ipsum dolor sit amet, consectetur adipiscing elit. Nulla ultrices dolor justo, vel egestas nunc mattis vitae. Aliquam erat volutpat. Nam faucibus urna non arcu ultrices efficitur. Phasellus ut aliquet odio, suscipit pulvinar purus. Proin a consequat augue. Praesent finibus odio vel pretium consequat. Lorem ipsum dolor sit amet, consectetur adipiscing elit. Nulla ultrices dolor justo, vel egestas nunc mattis vitae. Aliquam erat volutpat. Nam faucibus urna non arcu ultrices efficitur. Phasellus ut aliquet odio, suscipit pulvinar purus. Proin a consequat augue. Praesent finibus odio vel pretium consequat. Lorem ipsum dolor sit amet, consectetur adipiscing elit. Nulla ultrices dolor justo, vel egestas nunc mattis vitae. Aliquam erat volutpat. Nam faucibus urna non arcu ultrices efficitur. Phasellus ut aliquet odio, suscipit pulvinar purus. Proin a consequat augue. Praesent finibus odio vel pretium consequat. Lorem ipsum dolor sit amet, consectetur adipiscing elit. Nulla ultrices dolor justo, vel egestas nunc mattis vitae. Aliquam erat volutpat. Nam faucibus urna non arcu ultrices efficitur. Phasellus ut aliquet odio, suscipit pulvinar purus. Proin a consequat augue. Praesent finibus odio vel pretium consequat. Lorem ipsum dolor sit amet, consectetur adipiscing elit. Nulla ultrices dolor justo, vel egestas nunc mattis vitae. Aliquam erat volutpat. Nam faucibus urna non arcu ultrices efficitur. Phasellus ut aliquet odio, suscipit pulvinar purus. Proin a consequat augue. Praesent finibus odio vel pretium consequat. Lorem ipsum dolor sit amet, consectetur adipiscing elit. Nulla ultrices dolor justo, vel egestas nunc mattis vitae. Aliquam erat volutpat. Nam faucibus urna non arcu ultrices efficitur. Phasellus ut aliquet odio, suscipit pulvinar purus. Proin a consequat augue. Praesent finibus odio vel pretium consequat. Lorem ipsum dolor sit amet, consectetur adipiscing elit. Nulla ultrices dolor justo, vel egestas nunc mattis vitae. Aliquam erat volutpat. Nam faucibus urna non arcu ultrices efficitur. Phasellus ut aliquet odio, suscipit pulvinar purus. Proin a consequat augue. Praesent finibus odio vel pretium consequat. Lorem ipsum dolor sit amet, consectetur adipiscing elit. Nulla ultrices dolor justo, vel egestas nunc mattis vitae. Aliquam erat volutpat. Nam faucibus urna non arcu ultrices efficitur. Phasellus ut aliquet odio, suscipit pulvinar purus. Proin a consequat augue. Praesent finibus odio vel pretium consequat. Lorem ipsum dolor sit amet, consecte","image":"./images/articles/11.jpg","date_added":"2022-06-28"},"metadata":{"id":"articleId_11","type":"article","tags":["tag_0","tag_1","tag_2","tag_3"],"is_active":true}}}